MANIFEST.in
README.md
requirements.txt
setup.cfg
setup.py
DeepPurpose/CompoundPred.py
DeepPurpose/DDI.py
DeepPurpose/DTI.py
DeepPurpose/PPI.py
DeepPurpose/ProteinPred.py
DeepPurpose/__init__.py
DeepPurpose/chemutils.py
DeepPurpose/dataset.py
DeepPurpose/encoders.py
DeepPurpose/model_helper.py
DeepPurpose/oneliner.py
DeepPurpose/pybiomed_helper.py
DeepPurpose/utils.py
DeepPurpose.egg-info/PKG-INFO
DeepPurpose.egg-info/SOURCES.txt
DeepPurpose.egg-info/dependency_links.txt
DeepPurpose.egg-info/requires.txt
DeepPurpose.egg-info/top_level.txt
DeepPurpose/ESPF/drug_codes_chembl_freq_1500.txt
DeepPurpose/ESPF/protein_codes_uniprot_2000.txt
DeepPurpose/ESPF/subword_units_map_chembl_freq_1500.csv
DeepPurpose/ESPF/subword_units_map_uniprot_2000.csv