Metadata-Version: 2.1
Name: DeepPurpose
Version: 0.0.6
Summary: a Deep Learning Based Toolkit for Drug Discovery
Home-page: https://github.com/kexinhuang12345/DeepPurpose
Author: Kexin Huang, Tianfan Fu
Author-email: kexinhuang@hsph.harvard.edu
License: BSD-3-Clause
Platform: UNKNOWN
Classifier: Programming Language :: Python :: 3
Classifier: License :: OSI Approved :: BSD License
Classifier: Operating System :: OS Independent
